ksqldb_client/__init__.py
ksqldb_client/decorators.py
ksqldb_client/exceptions.py
ksqldb_client/models/__init__.py
ksqldb_client/models/base.py
ksqldb_client/models/info_response.py
ksqldb_client/models/ksql_response.py
ksqldb_client/models/query_response.py
ksqldb_client/models/status_response.py
ksqldb_client/testing/__init__.py
ksqldb_client/testing/parse.py
ksqldb_client/testing/to_timestamp.py
ksqldb_client-0.28.2a2.dist-info/LICENSE
ksqldb_client-0.28.2a2.dist-info/METADATA
ksqldb_client-0.28.2a2.dist-info/WHEEL
ksqldb_client-0.28.2a2.dist-info/RECORD
